dictdumper/__init__.py
dictdumper/_dateutil.py
dictdumper/_hexlify.py
dictdumper/_types.py
dictdumper/dumper.py
dictdumper/json.py
dictdumper/plist.py
dictdumper/tree.py
dictdumper/vuejs.py
dictdumper/xml.py
dictdumper-0.8.4.post6.dist-info/LICENSE
dictdumper-0.8.4.post6.dist-info/METADATA
dictdumper-0.8.4.post6.dist-info/WHEEL
dictdumper-0.8.4.post6.dist-info/top_level.txt
dictdumper-0.8.4.post6.dist-info/RECORD
