Metadata-Version: 2.1
Name: dictdumper
Version: 0.8.4.post6
Summary: DictDumper: comprehensive network packet analysis library
Author-email: Jarry Shaw <jarryshaw@icloud.com>
Maintainer: Jarry Shaw
License: BSD 3-Clause License
Project-URL: homepage, https://jarryshaw.github.io/DictDumper/
Project-URL: documentation, https://jarryshaw.github.io/DictDumper/
Project-URL: repository, https://github.com/JarryShaw/DictDumper
Project-URL: changelog, https://github.com/JarryShaw/DictDumper/releases
Keywords: formatting,dumper,stream
Classifier: Development Status :: 5 - Production/Stable
Classifier: Environment :: Console
Classifier: Environment :: MacOS X
Classifier: Environment :: Win32 (MS Windows)
Classifier: Intended Audience :: Developers
Classifier: License :: OSI Approved :: BSD License
Classifier: Natural Language :: English
Classifier: Operating System :: MacOS
Classifier: Operating System :: Microsoft :: Windows
Classifier: Operating System :: Unix
Classifier: Programming Language :: Python
Classifier: Programming Language :: Python :: 2
Classifier: Programming Language :: Python :: 2.7
Classifier: Programming Language :: Python :: 3
Classifier: Programming Language :: Python :: 3.0
Classifier: Programming Language :: Python :: 3.1
Classifier: Programming Language :: Python :: 3.2
Classifier: Programming Language :: Python :: 3.3
Classifier: Programming Language :: Python :: 3.4
Classifier: Programming Language :: Python :: 3.5
Classifier: Programming Language :: Python :: 3.6
Classifier: Programming Language :: Python :: 3.7
Classifier: Programming Language :: Python :: 3.8
Classifier: Programming Language :: Python :: Implementation
Classifier: Programming Language :: Python :: Implementation :: CPython
Classifier: Programming Language :: Python :: Implementation :: PyPy
Classifier: Topic :: System :: Networking
Classifier: Topic :: Utilities
Requires-Python: >=2.7
License-File: LICENSE
Requires-Dist: typing-extensions; python_version < "3.8"
Provides-Extra: docs
Requires-Dist: Sphinx>=6.1.3; extra == "docs"
Requires-Dist: sphinx-autodoc-typehints; extra == "docs"
Requires-Dist: sphinx-opengraph; extra == "docs"
Requires-Dist: sphinx-copybutton; extra == "docs"
Requires-Dist: furo; extra == "docs"
